{
    "name": "０》新手上路",
    "icon": "techguns:handcannon",
    "category": "survival_guide",
    "pages": [
        {
            "type": "text",
            "text": "在新的遊戲初期，很快就能開始使用科技槍械模組的武器。只需少許的原木和石頭，一個打火石加上一些火藥，就能輕易做出《手砲》。$(br)不過也可能會遇到手持科技槍械模組武器的敵人，需格外小心 ！"
        },
        {
            "type": "text",
            "title": "起步",
            "text": "首先盡量收集一些資源，像是鐵錠、煤炭，或許還有紅石。然後依安裝的模組，建造基本的能量生產裝置。當有能源後，就可建造科技槍械模組的首要機器：$(l:machines/metal_press)《金屬加壓機》$(/l)、$(l:machines/ammo_press)《彈藥壓製機》$(/l)、$(l:machines/chemical_laboratory)《化學加工機》$(/l)以及$(l:machines/blast_furnace)《高爐》$(/l)。而$(l:machines/camo_bench)《迷彩機》$(/l)及$(l:machines/repair_bench)《修理機》$(/l)雖然初期可能也會用到，但不是必要的。"
        },
        {
            "type": "text",
            "title": "獲得服裝",
            "text": "由於科技槍械模組的敵人都很危險，你最好能獲得前三套服裝中的一套。這三套為擁有最佳移動性能且非常適合偵察的『盜賊裝』，挖礦的最佳選擇『礦工裝』，以及最能在槍戰中提供保護的『士兵裝』。"
        },
        {
            "type": "text",
            "title": "獲得武器",
            "text": "別以為只用手槍就能對付全部的敵人，你需要更好的武器，而較好的槍都需要《鐵製機匣》來製作。$(br)《動力鎚》是很棒的挖礦工具，也應該盡早做一把來提升你的挖礦效率，之後還能升級至更高的挖礦等級。"
        }
    ]
}