{
  "display": {
    "icon": {
      "item": "minecraft:wet_sponge"
    },
    "title": {
      "translate": "advancements.the_guardian_is_just_a_joke_to_you.title"
    },
    "description": {
      "translate": "advancements.the_guardian_is_just_a_joke_to_you.descr"
    },
    "frame": "goal",
    "show_toast": true,
    "announce_to_chat": true,
    "hidden": false
  },
  "criteria": {
    "the_guardian_is_just_a_joke_to_you": {
      "trigger": "minecraft:impossible"
    }
  },
  "rewards": {
    "experience": 1
  },
  "parent": "minecraft:adventure/throw_trident"
}